compimg/__init__.py
compimg/exceptions.py
compimg/kernels.py
compimg/pads.py
compimg/similarity.py
compimg/windows.py
compimg/_internals/__init__.py
compimg/_internals/_decorators.py
compimg/_internals/_utilities.py
compimg-0.2.2.dist-info/LICENSE
compimg-0.2.2.dist-info/METADATA
compimg-0.2.2.dist-info/WHEEL
compimg-0.2.2.dist-info/top_level.txt
compimg-0.2.2.dist-info/RECORD
