Metadata-Version: 2.1
Name: compimg
Version: 0.2.2
Summary: Image similarity metrics.
Home-page: http://github.com/khrynczenko/compimg
Author: khrynczenko
Author-email: jeniopy@gmail.com
License: UNKNOWN
Platform: UNKNOWN
Classifier: Programming Language :: Python :: 3.6
Classifier: Programming Language :: Python :: 3.7
Classifier: Programming Language :: Python :: 3.8
Classifier: License :: OSI Approved :: Apache Software License
Classifier: Operating System :: OS Independent
Classifier: Topic :: Scientific/Engineering
Requires-Python: >=3.6
Requires-Dist: scipy (<2.0.0,>=1.1.0)
Requires-Dist: numpy (<2.0.0,>=1.15.4)
